clifpy/__init__.py
clifpy/clif_orchestrator.py
clifpy/data/__init__.py
clifpy/data/loader.py
clifpy/data/mdro.yaml
clifpy/data/clif_demo/clif_adt.parquet
clifpy/data/clif_demo/clif_code_status.parquet
clifpy/data/clif_demo/clif_crrt_therapy.parquet
clifpy/data/clif_demo/clif_hospital_diagnosis.parquet
clifpy/data/clif_demo/clif_hospitalization.parquet
clifpy/data/clif_demo/clif_labs.parquet
clifpy/data/clif_demo/clif_medication_admin_continuous.parquet
clifpy/data/clif_demo/clif_medication_admin_intermittent.parquet
clifpy/data/clif_demo/clif_patient.parquet
clifpy/data/clif_demo/clif_patient_assessments.parquet
clifpy/data/clif_demo/clif_patient_procedures.parquet
clifpy/data/clif_demo/clif_position.parquet
clifpy/data/clif_demo/clif_respiratory_support.parquet
clifpy/data/clif_demo/clif_vitals.parquet
clifpy/data/comorbidity/cci.yaml
clifpy/data/comorbidity/elixhauser.yaml
clifpy/schemas/adt_schema.yaml
clifpy/schemas/code_status_schema.yaml
clifpy/schemas/crrt_therapy_schema.yaml
clifpy/schemas/ecmo_mcs_schema.yaml
clifpy/schemas/hospital_diagnosis_schema.yaml
clifpy/schemas/hospitalization_schema.yaml
clifpy/schemas/labs_schema.yaml
clifpy/schemas/medication_admin_continuous_schema.yaml
clifpy/schemas/medication_admin_intermittent_schema.yaml
clifpy/schemas/microbiology_culture_schema.yaml
clifpy/schemas/microbiology_nonculture_schema.yaml
clifpy/schemas/microbiology_susceptibility_schema.yaml
clifpy/schemas/outlier_config.yaml
clifpy/schemas/patient_assessments_schema.yaml
clifpy/schemas/patient_procedures_schema.yaml
clifpy/schemas/patient_schema.yaml
clifpy/schemas/position_schema.yaml
clifpy/schemas/respiratory_support_schema.yaml
clifpy/schemas/vitals_schema.yaml
clifpy/schemas/wide_tables_config.yaml
clifpy/tables/__init__.py
clifpy/tables/adt.py
clifpy/tables/base_table.py
clifpy/tables/code_status.py
clifpy/tables/crrt_therapy.py
clifpy/tables/ecmo_mcs.py
clifpy/tables/hospital_diagnosis.py
clifpy/tables/hospitalization.py
clifpy/tables/labs.py
clifpy-0.3.8.dist-info/licenses/LICENSE
clifpy-0.3.8.dist-info/METADATA
clifpy-0.3.8.dist-info/WHEEL
clifpy-0.3.8.dist-info/top_level.txt
clifpy-0.3.8.dist-info/RECORD
