Metadata-Version: 2.4
Name: clifpy
Version: 0.3.8
Summary: A Python package for working with CLIF EHR data
Author-email: CLIF Consortium <clif_consortium@uchicago.edu>, Kaveri Chhikara <kaveri.chhikara@gmail.com>, Dema Therese Maria <theresemaria98@gmail.com>, Vaishvik Chaudhari <Vaishvikc@gmail.com>, Zewei 'Whiskey' Liao <whiskey0504@gmail.com>
License:                                  Apache License
Classifier: Programming Language :: Python :: 3.9
Classifier: License :: OSI Approved :: Apache Software License
Classifier: Operating System :: OS Independent
Requires-Python: >=3.9
License-File: LICENSE
Requires-Dist: pandas
Requires-Dist: duckdb
Requires-Dist: pyarrow
Requires-Dist: matplotlib
Requires-Dist: seaborn
Requires-Dist: pytest
Requires-Dist: pytz
Requires-Dist: tqdm
Requires-Dist: polars>=1.33.1
Requires-Dist: pyyaml>=6.0.2
Requires-Dist: psutil>=7.1.0
Requires-Dist: toml>=0.10.2
Requires-Dist: build>=1.3.0
Requires-Dist: twine>=6.2.0
Dynamic: license-file
